pingpong/__init__.py
pingpong/alpaca.py
pingpong/baize.py
pingpong/dolly.py
pingpong/flan.py
pingpong/gradio.py
pingpong/group.py
pingpong/guanaco.py
pingpong/koalpaca.py
pingpong/kullm.py
pingpong/mpt.py
pingpong/orca_mini.py
pingpong/os_stablelm.py
pingpong/pingpong.py
pingpong/redpajama.py
pingpong/stable_vicuna.py
pingpong/stablelm.py
pingpong/starchat.py
pingpong/utils.py
pingpong/vicuna.py
pingpong/wizard_falcon.py
pingpong/xgen.py
pingpong/context/__init__.py
pingpong/context/auto_summary_strategy.py
pingpong/context/internet_search_strategy.py
pingpong/context/last_window_strategy.py
pingpong/context/search_window_strategy.py
pingpong/context/strategy.py
bingbong-0.4.3.dist-info/LICENSE
bingbong-0.4.3.dist-info/METADATA
bingbong-0.4.3.dist-info/WHEEL
bingbong-0.4.3.dist-info/top_level.txt
bingbong-0.4.3.dist-info/RECORD
