Metadata-Version: 2.1
Name: bingbong
Version: 0.4.3
Summary: Ping pong is a management library for LLM applied applications.
Home-page: https://github.com/deep-diver/PingPong
Author: chansung park
Author-email: deep.diver.csp@gmail.com
Keywords: LLM,pingpong,prompt,context,management
Classifier: License :: OSI Approved :: Apache Software License
Classifier: Programming Language :: Python :: 3.8
Classifier: Programming Language :: Python :: 3.9
Classifier: Programming Language :: Python :: 3.10
Classifier: Programming Language :: Python :: 3.11
Requires-Python: >=3.8
License-File: LICENSE
Requires-Dist: chromadb
Requires-Dist: torch
Requires-Dist: transformers
Requires-Dist: bs4
